<?xml version="1.0" encoding="utf-8"?>
<!DOCTYPE hibernate-mapping PUBLIC "-//Hibernate/Hibernate Mapping DTD 3.0//EN"
"http://www.hibernate.org/dtd/hibernate-mapping-3.0.dtd">
<!-- 
    Mapping file autogenerated by MyEclipse Persistence Tools
-->
<hibernate-mapping>
    <class name="com.dtos.Reservation" table="RESERVATION" schema="LKJ" lazy="false" optimistic-lock="version">
        <id name="id" type="java.lang.Integer">
            <column name="ID" precision="22" scale="0" />
            <generator class="increment"></generator>
        </id>
        <version name="version" column="VERSION" type="int"></version>
        <many-to-one name="schoolLib" class="com.dtos.SchoolLib" fetch="select">
            <column name="L_ID" precision="22" scale="0" />
        </many-to-one>
        <many-to-one name="users" class="com.dtos.Users" fetch="select">
            <column name="U_ID" precision="22" scale="0" />
        </many-to-one>
        <property name="seat" type="java.lang.String">
            <column name="SEAT" length="20" />
        </property>
        <property name="state" type="java.lang.String">
            <column name="STATE" length="20" />
        </property>
        <property name="period" type="java.lang.String">
            <column name="PERIOD" length="20" />
        </property>
        <property name="TIME" type="java.lang.String">
            <column name="TIME" length="20" />
        </property>
    </class>
</hibernate-mapping>